README.md
setup.cfg
setup.py
quikkly_python_sdk.egg-info/PKG-INFO
quikkly_python_sdk.egg-info/SOURCES.txt
quikkly_python_sdk.egg-info/dependency_links.txt
quikkly_python_sdk.egg-info/requires.txt
quikkly_python_sdk.egg-info/top_level.txt
quikklysdk/__init__.py
quikklysdk/quikkly.py
quikklysdk/quikklycore.py
quikklysdk/quikklyutils.py
scripts/quikkly-generate-code.py
scripts/quikkly-scan-image.py
scripts/quikkly-template-info.py